dbk_aicode/__init__.py
dbk_aicode/base.py
dbk_aicode/db/__init__.py
dbk_aicode/db/base.py
dbk_aicode/js_agent/__init__.py
dbk_aicode/js_agent/base.py
dbk_aicode/js_agent/callbacks/__init__.py
dbk_aicode/js_agent/callbacks/log.py
dbk_aicode/js_agent/prompt.py
dbk_aicode/tools/__init__.py
dbk_aicode/tools/javascript/__init__.py
dbk_aicode/tools/javascript/eval.py
dbk_aicode/tools/javascript/tool.py
dbk_aicode-0.2.0.dist-info/METADATA
dbk_aicode-0.2.0.dist-info/WHEEL
dbk_aicode-0.2.0.dist-info/RECORD
