Metadata-Version: 2.1
Name: dbk-aicode
Version: 0.2.0
Summary: 
Author: Vasek Mlejnsky
Author-email: vasek.mlejnsky@gmail.com
Requires-Python: >=3.8.1,<4.0
Classifier: Programming Language :: Python :: 3
Classifier: Programming Language :: Python :: 3.9
Classifier: Programming Language :: Python :: 3.10
Classifier: Programming Language :: Python :: 3.11
Requires-Dist: langchain (>=0.0.102,<0.0.103)
Requires-Dist: openai (>=0.27.0,<0.28.0)
Requires-Dist: python-dotenv (>=1.0.0,<2.0.0)
Requires-Dist: supabase (>=1.0.1,<2.0.0)
